main.py
pentesttools/__init__.py
pentesttools/api.py
pentesttools/banner.py
pentesttools/cli.py
pentesttools/context.py
pentesttools/logger_config.py
pentesttools/mcp.py
pentesttools/text_format.py
pentesttools-0.1.5.dist-info/licenses/LICENSE
tests/test_cli.py
pentesttools-0.1.5.dist-info/METADATA
pentesttools-0.1.5.dist-info/WHEEL
pentesttools-0.1.5.dist-info/entry_points.txt
pentesttools-0.1.5.dist-info/top_level.txt
pentesttools-0.1.5.dist-info/RECORD
