Metadata-Version: 2.4
Name: pentesttools
Version: 0.1.5
Summary: Pentest-Tools.com Vulnerability Scanners Library
Author-email: The Pentest-Tools Team <contact@pentest-tools.com>
Requires-Python: >=3.10
License-File: LICENSE
Requires-Dist: requests>=2.31.0
Provides-Extra: dev
Requires-Dist: coverage; extra == "dev"
Provides-Extra: mcp
Requires-Dist: mcp>=1.4.1; extra == "mcp"
Requires-Dist: pydantic>=2.11.7; extra == "mcp"
Requires-Dist: fastmcp>=2.12.4; extra == "mcp"
Dynamic: license-file
